xclass_fb_sdk/__init__.py
xclass_fb_sdk/chat_bot_fb_app.py
xclass_fb_sdk/xclass_helpers.py
xclass_fb_sdk/chat_bot_fb/facebookApiSupporter.py
xclass_fb_sdk/chat_bot_fb/logic.py
xclass_fb_sdk/chat_bot_fb/main.py
xclass_fb_sdk/chat_bot_fb/requirements.txt
xclass_fb_sdk/chat_bot_fb/vercel.json
xclass_fb_sdk/chat_bot_fb/xClassService.py
xclass_fb_sdk-1.0.1.dist-info/LICENSE.txt
xclass_fb_sdk-1.0.1.dist-info/METADATA
xclass_fb_sdk-1.0.1.dist-info/WHEEL
xclass_fb_sdk-1.0.1.dist-info/top_level.txt
xclass_fb_sdk-1.0.1.dist-info/RECORD
